{
  "labels": {
    "analysis": "The MCP Server \"io.github.augiemazza/varrd\" provides 8 tools focused on web search & research tasks. Core capabilities include data access and reading, modification and updates, search and retrieval. Key tools: research, scan, search, get_hypothesis, check_balance.",
    "reasoning": "Primary label \"Web Search & Research\" assigned based on strong keyword matches in tool names and descriptions: search, research.",
    "primary_label": "Web Search & Research",
    "secondary_labels": [
      "Data Analysis & Processing",
      "Financial Services"
    ],
    "custom_label": "Data Access & Search - io.github.augiemazza/varrd",
    "is_connected": true,
    "is_remote_tool_valid": true,
    "featured_server": true,
    "tool_verified": false,
    "tool_verified_status": "tool_error",
    "tool_verified_at": "2026-03-14T20:38:13.843471+00:00",
    "tool_verified_tool": "search",
    "tool_verified_reason": "HTTP 400: {\"jsonrpc\": \"2.0\", \"id\": null, \"error\": {\"code\": -32600, \"message\": \"Missing Mcp-Session-Id header. "
  },
  "metadata": {
    "server_id": 99,
    "server_name": "io.github.augiemazza/varrd",
    "rank_by_usage": 100,
    "usage_count": "100",
    "original_file": "tools.json#99",
    "mode": "gateway",
    "timestamp": 1772876337,
    "remote_server_response": {
      "url": "https://app.varrd.com/mcp",
      "is_success": true,
      "error": null,
      "tools": [
        {
          "name": "research",
          "description": "Talk to VARRD AI — a quant research system with 15 internal tools. Describe any trading idea in plain language, or ask for specific capabilities like the ELROND expert council, backtesting, or stop-loss optimization.\n\nMULTI-TURN: First call creates a session. Keep calling with the same session_id, following context.next_actions each time.\n  1. Your idea -> VARRD charts pattern\n  2. 'test it' -> statistical test (event study or backtest)\n  3. 'show me the trade setup' -> exact entry/stop/target prices\n\nHYPOTHESIS INTEGRITY (critical):\nVARRD tests ONE hypothesis at a time — one formula, one setup. Never combine multiple setups into one formula or ask to 'test all' — each idea must be tested as a separate hypothesis for the statistics to be valid. Say 'start a new hypothesis' between ideas to reset cleanly.\n  - ALLOWED: Test the SAME setup across multiple markets ('test this on ES, NQ, and CL') — same formula, different data.\n  - NOT ALLOWED: Test multiple DIFFERENT formulas/setups at once — each is a separate hypothesis requiring its own chart-test-result cycle.\nIf ELROND council returns 4 setups, test each one separately: chart setup 1 -> test -> results -> 'start new hypothesis' -> chart setup 2 -> etc.\n\nKEY CAPABILITIES you can ask for:\n  - 'Use the ELROND council on [market]' -> 8 expert investigators\n  - 'Optimize the stop loss and take profit' -> SL/TP grid search\n  - 'Test this on ES, NQ, and CL' -> multi-market testing\n  - 'Simulate trading this with 1.5 ATR stop' -> backtest with stops\n\nEDGE VERDICTS in context.edge_verdict after testing:\n  - STRONG EDGE: Significant vs zero AND vs market baseline\n  - MARGINAL: Significant vs zero only (beats nothing, but real signal)\n  - PINNED: Significant vs market only (flat returns but different from market)\n  - NO EDGE: Neither significant test passed\n\nTERMINAL STATES: Stop when context.has_edge is true (edge found) or false (no edge — valid result). Always read context.next_actions.",
          "inputSchema": {
            "type": "object",
            "properties": {
              "message": {
                "type": "string",
                "description": "Your trading idea, research question, or instruction (e.g. 'test it', 'show trade setup')."
              },
              "session_id": {
                "type": "string",
                "description": "Session ID from a previous call. Omit to start a new research session."
              }
            },
            "required": [
              "message"
            ]
          },
          "annotations": {
            "title": "Research",
            "readOnlyHint": false,
            "destructiveHint": false,
            "idempotentHint": false,
            "openWorldHint": true
          }
        },
        {
          "name": "scan",
          "description": "Scan your saved strategies against current market data to see what's firing right now. Returns exact dollar entry, stop-loss, and take-profit prices for every active signal. Not a vague directional call — exact trade levels based on the validated statistical model.",
          "inputSchema": {
            "type": "object",
            "properties": {
              "market": {
                "type": "string",
                "description": "Filter by market symbol (e.g. 'ES', 'SPY'). Omit to scan all."
              },
              "only_firing": {
                "type": "boolean",
                "description": "If true, only return strategies that are firing right now.",
                "default": false
              }
            }
          },
          "annotations": {
            "title": "Scan Signals",
            "readOnlyHint": true,
            "destructiveHint": false,
            "idempotentHint": true,
            "openWorldHint": false
          }
        },
        {
          "name": "search",
          "description": "Search your saved hypotheses by keyword or natural language query. Returns matching strategies ranked by relevance, with key stats (win rate, Sharpe, edge status). Use this to find strategies you've already validated.",
          "inputSchema": {
            "type": "object",
            "properties": {
              "query": {
                "type": "string",
                "description": "Search query — keywords or natural language (e.g. 'momentum strategies', 'RSI oversold')."
              },
              "market": {
                "type": "string",
                "description": "Optional market filter."
              },
              "limit": {
                "type": "integer",
                "description": "Max results to return.",
                "default": 10
              }
            },
            "required": [
              "query"
            ]
          },
          "annotations": {
            "title": "Search Strategies",
            "readOnlyHint": true,
            "destructiveHint": false,
            "idempotentHint": true,
            "openWorldHint": false
          }
        },
        {
          "name": "get_hypothesis",
          "description": "Get full detail for a specific hypothesis/strategy. Returns formula, entry/exit rules, direction, performance metrics (win rate, Sharpe, profit factor, max drawdown), version history, and trade levels. Everything an agent needs to understand and act on a strategy.",
          "inputSchema": {
            "type": "object",
            "properties": {
              "hypothesis_id": {
                "type": "string",
                "description": "The hypothesis ID (from search or scan results)."
              }
            },
            "required": [
              "hypothesis_id"
            ]
          },
          "annotations": {
            "title": "Get Strategy Details",
            "readOnlyHint": true,
            "destructiveHint": false,
            "idempotentHint": true,
            "openWorldHint": false
          }
        },
        {
          "name": "check_balance",
          "description": "Check your credit balance and see available credit packs. Free — no credits consumed. Call this before heavy operations to ensure you have sufficient credits.",
          "inputSchema": {
            "type": "object",
            "properties": {}
          },
          "annotations": {
            "title": "Check Balance",
            "readOnlyHint": true,
            "destructiveHint": false,
            "idempotentHint": true,
            "openWorldHint": false
          }
        },
        {
          "name": "buy_credits",
          "description": "Buy credits with USDC on Base. Two modes:\n1. Call without payment_intent_id to get a Stripe deposit address.\n2. Send USDC to that address, then call again with the payment_intent_id to confirm and receive credits.\nDefault $5. Free — no credits consumed to call this.",
          "inputSchema": {
            "type": "object",
            "properties": {
              "amount_cents": {
                "type": "integer",
                "description": "Amount in cents (default 500 = $5.00). Minimum $5.",
                "default": 500
              },
              "payment_intent_id": {
                "type": "string",
                "description": "Stripe PaymentIntent ID from a previous buy_credits call. Pass this after sending USDC to confirm payment and receive credits."
              }
            }
          },
          "annotations": {
            "title": "Buy Credits",
            "readOnlyHint": false,
            "destructiveHint": false,
            "idempotentHint": false,
            "openWorldHint": true
          }
        },
        {
          "name": "reset_session",
          "description": "Kill a broken research session and start fresh. Use this when a session gets stuck, produces errors, or enters a bad state. Free — no credits consumed. After resetting, call research without a session_id to start a new clean session.",
          "inputSchema": {
            "type": "object",
            "properties": {
              "session_id": {
                "type": "string",
                "description": "The session_id to reset."
              }
            },
            "required": [
              "session_id"
            ]
          },
          "annotations": {
            "title": "Reset Session",
            "readOnlyHint": false,
            "destructiveHint": true,
            "idempotentHint": true,
            "openWorldHint": false
          }
        },
        {
          "name": "autonomous_research",
          "description": "Launch VARRD's autonomous research engine to discover and test a trading edge. Give it a topic and it handles everything: generates a creative hypothesis using its concept knowledge base, loads data, charts the pattern, runs the statistical test, and gets the trade setup if an edge is found.\n\nBEST FOR: Exploring a space broadly. The autonomous engine excels at tangential idea generation — give it 'momentum on grains' and it might test wheat seasonal patterns, corn spread reversals, or soybean crush ratio momentum. It propagates from your seed idea into related concepts you might not think of. Great for running many hypotheses at scale.\n\nReturns a complete result — edge/no edge, stats, trade setup. Each call tests ONE hypothesis through the full pipeline. Call again for another idea.\n\nUse 'research' instead when YOU have a specific idea to test and want full control over each step.",
          "inputSchema": {
            "type": "object",
            "properties": {
              "topic": {
                "type": "string",
                "description": "Research topic or trading idea (e.g. 'BTC 240min short setups', 'momentum on grains', 'mean reversion after VIX spikes')."
              },
              "markets": {
                "type": "array",
                "items": {
                  "type": "string"
                },
                "description": "Focus on specific markets (e.g. ['ES', 'NQ']). Omit for VARRD to choose."
              },
              "test_type": {
                "type": "string",
                "enum": [
                  "event_study",
                  "backtest",
                  "both"
                ],
                "description": "Type of statistical test. Default: event_study.",
                "default": "event_study"
              },
              "search_mode": {
                "type": "string",
                "enum": [
                  "focused",
                  "explore"
                ],
                "description": "focused = stay close to topic. explore = creative freedom. Default: focused.",
                "default": "focused"
              },
              "asset_classes": {
                "type": "array",
                "items": {
                  "type": "string",
                  "enum": [
                    "crypto",
                    "futures",
                    "equities"
                  ]
                },
                "description": "Limit to specific asset classes. Default: all."
              },
              "context": {
                "type": "array",
                "items": {
                  "type": "string"
                },
                "description": "Prior conversation context — recent user queries to use as research inspiration. Optional."
              }
            },
            "required": [
              "topic"
            ]
          },
          "annotations": {
            "title": "Autonomous Research",
            "readOnlyHint": false,
            "destructiveHint": false,
            "idempotentHint": false,
            "openWorldHint": true
          }
        }
      ],
      "tool_count": 8,
      "tool_names": [
        "research",
        "scan",
        "search",
        "get_hypothesis",
        "check_balance",
        "buy_credits",
        "reset_session",
        "autonomous_research"
      ]
    },
    "server_info_crawled": {
      "id": 99,
      "name": "io.github.augiemazza/varrd",
      "author": "",
      "overview": "io.github.augiemazza/varrd - Web Search & Research server with 8 tools. The MCP Server \"io.github.augiemazza/varrd\" provides 8 tools focused on web search & research tasks.",
      "repository_url": "",
      "homepage": "https://app.varrd.com/mcp",
      "remote_or_local": "Remote",
      "license": "",
      "usage_count": "100",
      "success_rate": "100%",
      "tags": [
        "web-search-research",
        "data-analysis-processing",
        "financial-services"
      ],
      "categories": [
        "web search & research",
        "data analysis & processing",
        "financial services"
      ],
      "tools_count": 8,
      "tools": [
        {
          "name": "research",
          "description": "Talk to VARRD AI — a quant research system with 15 internal tools. Describe any trading idea in plain language, or ask for specific capabilities like the ELROND expert council, backtesting, or stop-loss optimization.\n\nMULTI-TURN: First call creates a session. Keep calling with the same session_id, following context.next_actions each time.\n  1. Your idea -> VARRD charts pattern\n  2. 'test it' -> statistical test (event study or backtest)\n  3. 'show me the trade setup' -> exact entry/stop/target prices\n\nHYPOTHESIS INTEGRITY (critical):\nVARRD tests ONE hypothesis at a time — one formula, one setup. Never combine multiple setups into one formula or ask to 'test all' — each idea must be tested as a separate hypothesis for the statistics to be valid. Say 'start a new hypothesis' between ideas to reset cleanly.\n  - ALLOWED: Test the SAME setup across multiple markets ('test this on ES, NQ, and CL') — same formula, different data.\n  - NOT ALLOWED: Test multiple DIFFERENT formulas/setups at once — each is a separate hypothesis requiring its own chart-test-result cycle.\nIf ELROND council returns 4 setups, test each one separately: chart setup 1 -> test -> results -> 'start new hypothesis' -> chart setup 2 -> etc.\n\nKEY CAPABILITIES you can ask for:\n  - 'Use the ELROND council on [market]' -> 8 expert investigators\n  - 'Optimize the stop loss and take profit' -> SL/TP grid search\n  - 'Test this on ES, NQ, and CL' -> multi-market testing\n  - 'Simulate trading this with 1.5 ATR stop' -> backtest with stops\n\nEDGE VERDICTS in context.edge_verdict after testing:\n  - STRONG EDGE: Significant vs zero AND vs market baseline\n  - MARGINAL: Significant vs zero only (beats nothing, but real signal)\n  - PINNED: Significant vs market only (flat returns but different from market)\n  - NO EDGE: Neither significant test passed\n\nTERMINAL STATES: Stop when context.has_edge is true (edge found) or false (no edge — valid result). Always read context.next_actions.",
          "inputSchema": {
            "type": "object",
            "properties": {
              "message": {
                "type": "string",
                "description": "Your trading idea, research question, or instruction (e.g. 'test it', 'show trade setup')."
              },
              "session_id": {
                "type": "string",
                "description": "Session ID from a previous call. Omit to start a new research session."
              }
            },
            "required": [
              "message"
            ]
          },
          "annotations": {
            "title": "Research",
            "readOnlyHint": false,
            "destructiveHint": false,
            "idempotentHint": false,
            "openWorldHint": true
          }
        },
        {
          "name": "scan",
          "description": "Scan your saved strategies against current market data to see what's firing right now. Returns exact dollar entry, stop-loss, and take-profit prices for every active signal. Not a vague directional call — exact trade levels based on the validated statistical model.",
          "inputSchema": {
            "type": "object",
            "properties": {
              "market": {
                "type": "string",
                "description": "Filter by market symbol (e.g. 'ES', 'SPY'). Omit to scan all."
              },
              "only_firing": {
                "type": "boolean",
                "description": "If true, only return strategies that are firing right now.",
                "default": false
              }
            }
          },
          "annotations": {
            "title": "Scan Signals",
            "readOnlyHint": true,
            "destructiveHint": false,
            "idempotentHint": true,
            "openWorldHint": false
          }
        },
        {
          "name": "search",
          "description": "Search your saved hypotheses by keyword or natural language query. Returns matching strategies ranked by relevance, with key stats (win rate, Sharpe, edge status). Use this to find strategies you've already validated.",
          "inputSchema": {
            "type": "object",
            "properties": {
              "query": {
                "type": "string",
                "description": "Search query — keywords or natural language (e.g. 'momentum strategies', 'RSI oversold')."
              },
              "market": {
                "type": "string",
                "description": "Optional market filter."
              },
              "limit": {
                "type": "integer",
                "description": "Max results to return.",
                "default": 10
              }
            },
            "required": [
              "query"
            ]
          },
          "annotations": {
            "title": "Search Strategies",
            "readOnlyHint": true,
            "destructiveHint": false,
            "idempotentHint": true,
            "openWorldHint": false
          }
        },
        {
          "name": "get_hypothesis",
          "description": "Get full detail for a specific hypothesis/strategy. Returns formula, entry/exit rules, direction, performance metrics (win rate, Sharpe, profit factor, max drawdown), version history, and trade levels. Everything an agent needs to understand and act on a strategy.",
          "inputSchema": {
            "type": "object",
            "properties": {
              "hypothesis_id": {
                "type": "string",
                "description": "The hypothesis ID (from search or scan results)."
              }
            },
            "required": [
              "hypothesis_id"
            ]
          },
          "annotations": {
            "title": "Get Strategy Details",
            "readOnlyHint": true,
            "destructiveHint": false,
            "idempotentHint": true,
            "openWorldHint": false
          }
        },
        {
          "name": "check_balance",
          "description": "Check your credit balance and see available credit packs. Free — no credits consumed. Call this before heavy operations to ensure you have sufficient credits.",
          "inputSchema": {
            "type": "object",
            "properties": {}
          },
          "annotations": {
            "title": "Check Balance",
            "readOnlyHint": true,
            "destructiveHint": false,
            "idempotentHint": true,
            "openWorldHint": false
          }
        },
        {
          "name": "buy_credits",
          "description": "Buy credits with USDC on Base. Two modes:\n1. Call without payment_intent_id to get a Stripe deposit address.\n2. Send USDC to that address, then call again with the payment_intent_id to confirm and receive credits.\nDefault $5. Free — no credits consumed to call this.",
          "inputSchema": {
            "type": "object",
            "properties": {
              "amount_cents": {
                "type": "integer",
                "description": "Amount in cents (default 500 = $5.00). Minimum $5.",
                "default": 500
              },
              "payment_intent_id": {
                "type": "string",
                "description": "Stripe PaymentIntent ID from a previous buy_credits call. Pass this after sending USDC to confirm payment and receive credits."
              }
            }
          },
          "annotations": {
            "title": "Buy Credits",
            "readOnlyHint": false,
            "destructiveHint": false,
            "idempotentHint": false,
            "openWorldHint": true
          }
        },
        {
          "name": "reset_session",
          "description": "Kill a broken research session and start fresh. Use this when a session gets stuck, produces errors, or enters a bad state. Free — no credits consumed. After resetting, call research without a session_id to start a new clean session.",
          "inputSchema": {
            "type": "object",
            "properties": {
              "session_id": {
                "type": "string",
                "description": "The session_id to reset."
              }
            },
            "required": [
              "session_id"
            ]
          },
          "annotations": {
            "title": "Reset Session",
            "readOnlyHint": false,
            "destructiveHint": true,
            "idempotentHint": true,
            "openWorldHint": false
          }
        },
        {
          "name": "autonomous_research",
          "description": "Launch VARRD's autonomous research engine to discover and test a trading edge. Give it a topic and it handles everything: generates a creative hypothesis using its concept knowledge base, loads data, charts the pattern, runs the statistical test, and gets the trade setup if an edge is found.\n\nBEST FOR: Exploring a space broadly. The autonomous engine excels at tangential idea generation — give it 'momentum on grains' and it might test wheat seasonal patterns, corn spread reversals, or soybean crush ratio momentum. It propagates from your seed idea into related concepts you might not think of. Great for running many hypotheses at scale.\n\nReturns a complete result — edge/no edge, stats, trade setup. Each call tests ONE hypothesis through the full pipeline. Call again for another idea.\n\nUse 'research' instead when YOU have a specific idea to test and want full control over each step.",
          "inputSchema": {
            "type": "object",
            "properties": {
              "topic": {
                "type": "string",
                "description": "Research topic or trading idea (e.g. 'BTC 240min short setups', 'momentum on grains', 'mean reversion after VIX spikes')."
              },
              "markets": {
                "type": "array",
                "items": {
                  "type": "string"
                },
                "description": "Focus on specific markets (e.g. ['ES', 'NQ']). Omit for VARRD to choose."
              },
              "test_type": {
                "type": "string",
                "enum": [
                  "event_study",
                  "backtest",
                  "both"
                ],
                "description": "Type of statistical test. Default: event_study.",
                "default": "event_study"
              },
              "search_mode": {
                "type": "string",
                "enum": [
                  "focused",
                  "explore"
                ],
                "description": "focused = stay close to topic. explore = creative freedom. Default: focused.",
                "default": "focused"
              },
              "asset_classes": {
                "type": "array",
                "items": {
                  "type": "string",
                  "enum": [
                    "crypto",
                    "futures",
                    "equities"
                  ]
                },
                "description": "Limit to specific asset classes. Default: all."
              },
              "context": {
                "type": "array",
                "items": {
                  "type": "string"
                },
                "description": "Prior conversation context — recent user queries to use as research inspiration. Optional."
              }
            },
            "required": [
              "topic"
            ]
          },
          "annotations": {
            "title": "Autonomous Research",
            "readOnlyHint": false,
            "destructiveHint": false,
            "idempotentHint": false,
            "openWorldHint": true
          }
        }
      ],
      "python_sdk_url": "https://app.varrd.com/mcp",
      "python_sdk_config": "{\"debug\": false}"
    },
    "source_filename": "0099.iogithubaugiemazzavarrd_labeled.json",
    "processed_timestamp": 1772876337,
    "processing_mode": "gateway",
    "rank": 100
  }
}