{
  "labels": {
    "analysis": "The MCP Server \"com.supplymaven/risk-intelligence\" provides 7 tools focused on gaming tasks. Core capabilities include data access and reading. Key tools: get_supply_chain_risk, get_pillar_scores, get_manufacturing_index, get_commodity_prices, get_port_congestion.",
    "reasoning": "Primary label \"Gaming\" assigned based on strong keyword matches in tool names and descriptions: score, sport.",
    "primary_label": "Gaming",
    "secondary_labels": [
      "Financial Services",
      "Data Analysis & Processing"
    ],
    "custom_label": "Data Access - com.supplymaven/risk-intelligence",
    "is_connected": true,
    "is_remote_tool_valid": true,
    "featured_server": true,
    "tool_verified": false,
    "tool_verified_status": "auth_required",
    "tool_verified_at": "2026-03-14T20:38:15.361835+00:00",
    "tool_verified_tool": "get_supply_chain_risk",
    "tool_verified_reason": "auth error in response: event: message\ndata: {\"result\":{\"content\":[{\"type\":\"text\",\"text\":\"API key required. Get a free key i"
  },
  "metadata": {
    "server_id": 123,
    "server_name": "com.supplymaven/risk-intelligence",
    "rank_by_usage": 124,
    "usage_count": "100",
    "original_file": "tools.json#123",
    "mode": "gateway",
    "timestamp": 1772876337,
    "remote_server_response": {
      "url": "https://www.supplymaven.com/api/mcp",
      "is_success": true,
      "error": null,
      "tools": [
        {
          "name": "get_supply_chain_risk",
          "description": "Get the Global Disruption Index (GDI) — a 0-100 composite score of supply chain risk. Higher = more risk.",
          "inputSchema": {
            "$schema": "http://json-schema.org/draft-07/schema#",
            "type": "object",
            "properties": {}
          },
          "execution": {
            "taskSupport": "forbidden"
          }
        },
        {
          "name": "get_pillar_scores",
          "description": "Get individual GDI pillar scores: Energy (25%), Materials (25%), Transportation (30%), Macro (20%). Paid tier only.",
          "inputSchema": {
            "$schema": "http://json-schema.org/draft-07/schema#",
            "type": "object",
            "properties": {}
          },
          "execution": {
            "taskSupport": "forbidden"
          }
        },
        {
          "name": "get_manufacturing_index",
          "description": "Get the Supply Maven Manufacturing Index (SMI) — a proprietary weather-adjusted electricity demand indicator. INVERTED scale: lower = stronger manufacturing. 0-35 STRONG, 36-50 NORMAL, 51-65 BELOW TREND, 66+ WEAK.",
          "inputSchema": {
            "$schema": "http://json-schema.org/draft-07/schema#",
            "type": "object",
            "properties": {}
          },
          "execution": {
            "taskSupport": "forbidden"
          }
        },
        {
          "name": "get_commodity_prices",
          "description": "Get latest commodity prices relevant to supply chain risk. Free tier: 5 key commodities. Paid: all tracked commodities.",
          "inputSchema": {
            "$schema": "http://json-schema.org/draft-07/schema#",
            "type": "object",
            "properties": {}
          },
          "execution": {
            "taskSupport": "forbidden"
          }
        },
        {
          "name": "get_port_congestion",
          "description": "Get port congestion data — vessel counts, congestion scores, and stationary vessel ratios for major global ports. Paid tier only.",
          "inputSchema": {
            "$schema": "http://json-schema.org/draft-07/schema#",
            "type": "object",
            "properties": {}
          },
          "execution": {
            "taskSupport": "forbidden"
          }
        },
        {
          "name": "get_disruption_alerts",
          "description": "Get recent supply chain disruption alerts from news intelligence. Free tier: CRITICAL severity only. Paid: all severities.",
          "inputSchema": {
            "$schema": "http://json-schema.org/draft-07/schema#",
            "type": "object",
            "properties": {}
          },
          "execution": {
            "taskSupport": "forbidden"
          }
        },
        {
          "name": "get_sector_demand",
          "description": "Get electricity sector demand breakdown (industrial vs commercial ratios) across 8 US grid regions. Reveals data center / AI growth contamination signals. Paid tier only.",
          "inputSchema": {
            "$schema": "http://json-schema.org/draft-07/schema#",
            "type": "object",
            "properties": {}
          },
          "execution": {
            "taskSupport": "forbidden"
          }
        }
      ],
      "tool_count": 7,
      "tool_names": [
        "get_supply_chain_risk",
        "get_pillar_scores",
        "get_manufacturing_index",
        "get_commodity_prices",
        "get_port_congestion",
        "get_disruption_alerts",
        "get_sector_demand"
      ]
    },
    "server_info_crawled": {
      "id": 123,
      "name": "com.supplymaven/risk-intelligence",
      "author": "",
      "overview": "com.supplymaven/risk-intelligence - Gaming server with 7 tools. The MCP Server \"com.supplymaven/risk-intelligence\" provides 7 tools focused on gaming tasks. Core ca",
      "repository_url": "",
      "homepage": "https://www.supplymaven.com/api/mcp",
      "remote_or_local": "Remote",
      "license": "",
      "usage_count": "100",
      "success_rate": "100%",
      "tags": [
        "gaming",
        "financial-services",
        "data-analysis-processing"
      ],
      "categories": [
        "gaming",
        "financial services",
        "data analysis & processing"
      ],
      "tools_count": 7,
      "tools": [
        {
          "name": "get_supply_chain_risk",
          "description": "Get the Global Disruption Index (GDI) — a 0-100 composite score of supply chain risk. Higher = more risk.",
          "inputSchema": {
            "$schema": "http://json-schema.org/draft-07/schema#",
            "type": "object",
            "properties": {}
          },
          "execution": {
            "taskSupport": "forbidden"
          }
        },
        {
          "name": "get_pillar_scores",
          "description": "Get individual GDI pillar scores: Energy (25%), Materials (25%), Transportation (30%), Macro (20%). Paid tier only.",
          "inputSchema": {
            "$schema": "http://json-schema.org/draft-07/schema#",
            "type": "object",
            "properties": {}
          },
          "execution": {
            "taskSupport": "forbidden"
          }
        },
        {
          "name": "get_manufacturing_index",
          "description": "Get the Supply Maven Manufacturing Index (SMI) — a proprietary weather-adjusted electricity demand indicator. INVERTED scale: lower = stronger manufacturing. 0-35 STRONG, 36-50 NORMAL, 51-65 BELOW TREND, 66+ WEAK.",
          "inputSchema": {
            "$schema": "http://json-schema.org/draft-07/schema#",
            "type": "object",
            "properties": {}
          },
          "execution": {
            "taskSupport": "forbidden"
          }
        },
        {
          "name": "get_commodity_prices",
          "description": "Get latest commodity prices relevant to supply chain risk. Free tier: 5 key commodities. Paid: all tracked commodities.",
          "inputSchema": {
            "$schema": "http://json-schema.org/draft-07/schema#",
            "type": "object",
            "properties": {}
          },
          "execution": {
            "taskSupport": "forbidden"
          }
        },
        {
          "name": "get_port_congestion",
          "description": "Get port congestion data — vessel counts, congestion scores, and stationary vessel ratios for major global ports. Paid tier only.",
          "inputSchema": {
            "$schema": "http://json-schema.org/draft-07/schema#",
            "type": "object",
            "properties": {}
          },
          "execution": {
            "taskSupport": "forbidden"
          }
        },
        {
          "name": "get_disruption_alerts",
          "description": "Get recent supply chain disruption alerts from news intelligence. Free tier: CRITICAL severity only. Paid: all severities.",
          "inputSchema": {
            "$schema": "http://json-schema.org/draft-07/schema#",
            "type": "object",
            "properties": {}
          },
          "execution": {
            "taskSupport": "forbidden"
          }
        },
        {
          "name": "get_sector_demand",
          "description": "Get electricity sector demand breakdown (industrial vs commercial ratios) across 8 US grid regions. Reveals data center / AI growth contamination signals. Paid tier only.",
          "inputSchema": {
            "$schema": "http://json-schema.org/draft-07/schema#",
            "type": "object",
            "properties": {}
          },
          "execution": {
            "taskSupport": "forbidden"
          }
        }
      ],
      "python_sdk_url": "https://www.supplymaven.com/api/mcp",
      "python_sdk_config": "{\"debug\": false}"
    },
    "source_filename": "0123.comsupplymavenrisk-intelligence_labeled.json",
    "processed_timestamp": 1772876337,
    "processing_mode": "gateway",
    "rank": 124
  }
}